tenff/__init__.py
tenff/__main__.py
tenff/data/albanian-advanced.txt
tenff/data/albanian.txt
tenff/data/aoeu-dutch.txt
tenff/data/aoeu-english.txt
tenff/data/arabic.txt
tenff/data/armenian.txt
tenff/data/azerbaijani-advanced.txt
tenff/data/azerbaijani.txt
tenff/data/bengali.txt
tenff/data/bulgarian.txt
tenff/data/catalan-advanced.txt
tenff/data/catalan.txt
tenff/data/croatian.txt
tenff/data/czech-advanced.txt
tenff/data/czech.txt
tenff/data/danish-advanced.txt
tenff/data/danish.txt
tenff/data/dutch-advanced.txt
tenff/data/dutch.txt
tenff/data/english-advanced.txt
tenff/data/english.txt
tenff/data/esperanto.txt
tenff/data/estonian.txt
tenff/data/filipino.txt
tenff/data/finnish-advanced.txt
tenff/data/finnish.txt
tenff/data/french-advanced.txt
tenff/data/french.txt
tenff/data/galician-advanced.txt
tenff/data/galician.txt
tenff/data/georgian.txt
tenff/data/german-advanced.txt
tenff/data/german.txt
tenff/data/greek.txt
tenff/data/hebrew-advanced.txt
tenff/data/hebrew.txt
tenff/data/hindi-advanced.txt
tenff/data/hindi.txt
tenff/data/hungarian-advanced.txt
tenff/data/hungarian.txt
tenff/data/icelandic-advanced.txt
tenff/data/icelandic.txt
tenff/data/indonesian-advanced.txt
tenff/data/indonesian.txt
tenff/data/italian-advanced.txt
tenff/data/italian.txt
tenff/data/japanese-advanced.txt
tenff/data/japanese.txt
tenff/data/korean.txt
tenff/data/kurdish.txt
tenff/data/latvian.txt
tenff/data/lithuanian-advanced.txt
tenff/data/lithuanian.txt
tenff/data/macedonian.txt
tenff/data/malagasy.txt
tenff/data/malaysian-advanced.txt
tenff/data/malaysian.txt
tenff/data/norwegian-advanced.txt
tenff/data/norwegian.txt
tenff/data/pashto.txt
tenff/data/persian-advanced.txt
tenff/data/persian.txt
tenff/data/polish-advanced.txt
tenff/data/polish.txt
tenff/data/portuguese-advanced.txt
tenff/data/portuguese.txt
tenff/data/romanian-advanced.txt
tenff/data/romanian.txt
tenff/data/russian-advanced.txt
tenff/data/russian.txt
tenff/data/serbian.txt
tenff/data/simplified-chinese-advanced.txt
tenff-0.1.dist-info/entry_points.txt
tenff-0.1.dist-info/LICENSE.md
tenff-0.1.dist-info/WHEEL
tenff-0.1.dist-info/METADATA
tenff-0.1.dist-info/RECORD
